aws_pcluster_dask_gateway/__init__.py
aws_pcluster_dask_gateway/_version.py
aws_pcluster_dask_gateway/aws_pcluster_dask_gateway.py
aws_pcluster_dask_gateway/cli.py
aws_pcluster_dask_gateway-3.5.10.dist-info/LICENSE
aws_pcluster_dask_gateway-3.5.10.dist-info/METADATA
aws_pcluster_dask_gateway-3.5.10.dist-info/WHEEL
aws_pcluster_dask_gateway-3.5.10.dist-info/entry_points.txt
aws_pcluster_dask_gateway-3.5.10.dist-info/top_level.txt
aws_pcluster_dask_gateway-3.5.10.dist-info/RECORD
