Metadata-Version: 2.1
Name: aws-pcluster-dask-gateway
Version: 3.5.10
Summary: A helper function to configure Dask Gateway to play nice with AWS PCluster
Home-page: https://github.com/dabble-of-devops-bioanalyze/aws_pcluster_dask_gateway
Author: Jillian Rowe
Author-email: jillian@dabbleofdevops.com
License: Apache Software License 2.0
Keywords: aws_pcluster_dask_gateway
Classifier: Development Status :: 2 - Pre-Alpha
Classifier: Intended Audience :: Developers
Classifier: License :: OSI Approved :: Apache Software License
Classifier: Natural Language :: English
Classifier: Programming Language :: Python :: 3
Classifier: Programming Language :: Python :: 3.6
Classifier: Programming Language :: Python :: 3.7
Classifier: Programming Language :: Python :: 3.8
Requires-Python: >=3.6
License-File: LICENSE
Requires-Dist: dask-gateway-server
Requires-Dist: datasize
Requires-Dist: humanize
Requires-Dist: pydantic >2
Requires-Dist: aws-pcluster-helpers >=3.5
Requires-Dist: typer
